LinuxShellJiaobenJiaocheng30FenzhongWanzhuanShellJiaobenBiancheng/README.md
LinuxShellJiaobenJiaocheng30FenzhongWanzhuanShellJiaobenBiancheng/__init__.py
LinuxShellJiaobenJiaocheng30FenzhongWanzhuanShellJiaobenBiancheng/__main__.py
LinuxShellJiaobenJiaocheng30FenzhongWanzhuanShellJiaobenBiancheng/file.epub
LinuxShellJiaobenJiaocheng30FenzhongWanzhuanShellJiaobenBiancheng/index.html
LinuxShellJiaobenJiaocheng30FenzhongWanzhuanShellJiaobenBiancheng/css/__init__.py
LinuxShellJiaobenJiaocheng30FenzhongWanzhuanShellJiaobenBiancheng/css/annotations.css
LinuxShellJiaobenJiaocheng30FenzhongWanzhuanShellJiaobenBiancheng/css/main.css
LinuxShellJiaobenJiaocheng30FenzhongWanzhuanShellJiaobenBiancheng/css/normalize.css
LinuxShellJiaobenJiaocheng30FenzhongWanzhuanShellJiaobenBiancheng/css/popup.css
LinuxShellJiaobenJiaocheng30FenzhongWanzhuanShellJiaobenBiancheng/font/__init__.py
LinuxShellJiaobenJiaocheng30FenzhongWanzhuanShellJiaobenBiancheng/font/fontello.eot
LinuxShellJiaobenJiaocheng30FenzhongWanzhuanShellJiaobenBiancheng/font/fontello.svg
LinuxShellJiaobenJiaocheng30FenzhongWanzhuanShellJiaobenBiancheng/font/fontello.ttf
LinuxShellJiaobenJiaocheng30FenzhongWanzhuanShellJiaobenBiancheng/font/fontello.woff
LinuxShellJiaobenJiaocheng30FenzhongWanzhuanShellJiaobenBiancheng/img/__init__.py
LinuxShellJiaobenJiaocheng30FenzhongWanzhuanShellJiaobenBiancheng/img/annotator-glyph-sprite.png
LinuxShellJiaobenJiaocheng30FenzhongWanzhuanShellJiaobenBiancheng/img/annotator-icon-sprite.png
LinuxShellJiaobenJiaocheng30FenzhongWanzhuanShellJiaobenBiancheng/img/apple-touch-icon.png
LinuxShellJiaobenJiaocheng30FenzhongWanzhuanShellJiaobenBiancheng/img/cancelfullscreen.png
LinuxShellJiaobenJiaocheng30FenzhongWanzhuanShellJiaobenBiancheng/img/close.png
LinuxShellJiaobenJiaocheng30FenzhongWanzhuanShellJiaobenBiancheng/img/fullscreen.png
LinuxShellJiaobenJiaocheng30FenzhongWanzhuanShellJiaobenBiancheng/img/loader.gif
linux_shell_jiaoben_jiaocheng_30_fenzhong_wanzhuan_shell_jiaoben_biancheng-2024.3.2.0.dist-info/METADATA
linux_shell_jiaoben_jiaocheng_30_fenzhong_wanzhuan_shell_jiaoben_biancheng-2024.3.2.0.dist-info/WHEEL
linux_shell_jiaoben_jiaocheng_30_fenzhong_wanzhuan_shell_jiaoben_biancheng-2024.3.2.0.dist-info/entry_points.txt
linux_shell_jiaoben_jiaocheng_30_fenzhong_wanzhuan_shell_jiaoben_biancheng-2024.3.2.0.dist-info/top_level.txt
linux_shell_jiaoben_jiaocheng_30_fenzhong_wanzhuan_shell_jiaoben_biancheng-2024.3.2.0.dist-info/RECORD
